[{
    "image": "assets/images/brands/img-01.png",
    "eventName": "Tech Innovations Summit",
    "eventDate": "2024-06-15",
    "time": "09:00 AM",
    "peopleSize": "500",
    "location": "New York, NY",
    "eventType": "Offline",
    "price": "$899",
    "status": "Published"
  },
  {
    "image": "assets/images/brands/img-02.png",
    "eventName": "Marketing Strategies 2024",
    "eventDate": "2024-07-20",
    "time": "10:00 AM",
    "peopleSize": "300",
    "location": "San Francisco, CA",
    "eventType": "Offline",
    "price": "$499",
    "status": "Published"
  },
  {
    "image": "assets/images/brands/img-03.png",
    "eventName": "AI & Machine Learning Expo",
    "eventDate": "2024-08-10",
    "time": "11:00 AM",
    "peopleSize": "800",
    "location": "Chicago, IL",
    "eventType": "Online",
    "price": "$599",
    "status": "Coming Soon"
  },
  {
    "image": "assets/images/brands/img-04.png",
    "eventName": "Blockchain World Conference",
    "eventDate": "2024-09-05",
    "time": "09:30 AM",
    "peopleSize": "1000",
    "location": "Los Angeles, CA",
    "eventType": "Offline",
    "price": "$1099",
    "status": "Published"
  },
  {
    "image": "assets/images/brands/img-05.png",
    "eventName": "Cybersecurity Summit",
    "eventDate": "2024-10-18",
    "time": "10:30 AM",
    "peopleSize": "600",
    "location": "Boston, MA",
    "eventType": "Offline",
    "price": "$799",
    "status": "Published"
  },
  {
    "image": "assets/images/brands/img-06.png",
    "eventName": "Healthcare Innovations Forum",
    "eventDate": "2024-11-15",
    "time": "12:00 PM",
    "peopleSize": "400",
    "location": "Seattle, WA",
    "eventType": "Online",
    "price": "$399",
    "status": "Coming Soon"
  },
  {
    "image": "assets/images/brands/img-07.png",
    "eventName": "E-commerce Trends 2024",
    "eventDate": "2024-12-05",
    "time": "01:00 PM",
    "peopleSize": "700",
    "location": "Austin, TX",
    "eventType": "Offline",
    "price": "$699",
    "status": "Published"
  },
  {
    "image": "assets/images/brands/img-08.png",
    "eventName": "Fintech Conference",
    "eventDate": "2024-06-30",
    "time": "09:00 AM",
    "peopleSize": "200",
    "location": "Miami, FL",
    "eventType": "Online",
    "price": "$499",
    "status": "Expired"
  },
  {
    "image": "assets/images/brands/img-09.png",
    "eventName": "Digital Transformation Summit",
    "eventDate": "2024-07-25",
    "time": "09:00 AM",
    "peopleSize": "900",
    "location": "Dallas, TX",
    "eventType": "Offline",
    "price": "$899",
    "status": "Published"
  },
  {
    "image": "assets/images/brands/img-10.png",
    "eventName": "Green Technology Expo",
    "eventDate": "2024-08-15",
    "time": "10:00 AM",
    "peopleSize": "500",
    "location": "Denver, CO",
    "eventType": "Online",
    "price": "$599",
    "status": "Coming Soon"
  },
  {
    "image": "assets/images/brands/img-11.png",
    "eventName": "Smart Cities Conference",
    "eventDate": "2024-09-10",
    "time": "11:00 AM",
    "peopleSize": "600",
    "location": "Las Vegas, NV",
    "eventType": "Offline",
    "price": "$999",
    "status": "Published"
  },
  {
    "image": "assets/images/brands/img-12.png",
    "eventName": "Virtual Reality Expo",
    "eventDate": "2024-10-22",
    "time": "12:00 PM",
    "peopleSize": "300",
    "location": "Orlando, FL",
    "eventType": "Online",
    "price": "$399",
    "status": "Coming Soon"
  },
  {
    "image": "assets/images/brands/img-13.png",
    "eventName": "Renewable Energy Summit",
    "eventDate": "2024-11-05",
    "time": "09:00 AM",
    "peopleSize": "1000",
    "location": "San Diego, CA",
    "eventType": "Offline",
    "price": "$1099",
    "status": "Published"
  },
  {
    "image": "assets/images/brands/img-14.png",
    "eventName": "IoT World Forum",
    "eventDate": "2024-12-01",
    "time": "10:00 AM",
    "peopleSize": "700",
    "location": "Phoenix, AZ",
    "eventType": "Online",
    "price": "$499",
    "status": "Published"
  },
  {
    "image": "assets/images/brands/img-15.png",
    "eventName": "EdTech Conference",
    "eventDate": "2024-08-25",
    "time": "11:00 AM",
    "peopleSize": "400",
    "location": "Houston, TX",
    "eventType": "Offline",
    "price": "$699",
    "status": "Coming Soon"
  },
  {
    "image": "assets/images/brands/img-16.png",
    "eventName": "Cloud Computing Summit",
    "eventDate": "2024-09-18",
    "time": "12:00 PM",
    "peopleSize": "800",
    "location": "Salt Lake City, UT",
    "eventType": "Offline",
    "price": "$899",
    "status": "Published"
  },
  {
    "image": "assets/images/brands/img-17.png",
    "eventName": "Big Data & Analytics Forum",
    "eventDate": "2024-10-30",
    "time": "09:30 AM",
    "peopleSize": "500",
    "location": "Atlanta, GA",
    "eventType": "Online",
    "price": "$599",
    "status": "Coming Soon"
  },
  {
    "image": "assets/images/brands/img-18.png",
    "eventName": "SaaS Growth Conference",
    "eventDate": "2024-11-20",
    "time": "10:30 AM",
    "peopleSize": "600",
    "location": "Portland, OR",
    "eventType": "Offline",
    "price": "$799",
    "status": "Published"
  },
  {
    "image": "assets/images/brands/img-19.png",
    "eventName": "Digital Health Summit",
    "eventDate": "2024-12-10",
    "time": "11:00 AM",
    "peopleSize": "300",
    "location": "Nashville, TN",
    "eventType": "Online",
    "price": "$499",
    "status": "Coming Soon"
  },
  {
    "image": "assets/images/brands/img-20.png",
    "eventName": "Startup Pitch Event",
    "eventDate": "2024-07-10",
    "time": "12:00 PM",
    "peopleSize": "200",
    "location": "Raleigh, NC",
    "eventType": "Offline",
    "price": "$299",
    "status": "Expired"
  },
  {
    "image": "assets/images/brands/img-21.png",
    "eventName": "Wearable Tech Expo",
    "eventDate": "2024-09-25",
    "time": "09:00 AM",
    "peopleSize": "500",
    "location": "San Jose, CA",
    "eventType": "Offline",
    "price": "$599",
    "status": "Published"
  },
  {
    "image": "assets/images/brands/img-22.png",
    "eventName": "Autonomous Vehicles Summit",
    "eventDate": "2024-10-12",
    "time": "10:00 AM",
    "peopleSize": "700",
    "location": "Detroit, MI",
    "eventType": "Offline",
    "price": "$899",
    "status": "Published"
  },
  {
    "image": "assets/images/brands/img-23.png",
    "eventName": "Robotics Conference",
    "eventDate": "2024-11-03",
    "time": "11:00 AM",
    "peopleSize": "600",
    "location": "Pittsburgh, PA",
    "eventType": "Online",
    "price": "$499",
    "status": "Coming Soon"
  },
  {
    "image": "assets/images/brands/img-24.png",
    "eventName": "Space Technology Forum",
    "eventDate": "2024-12-15",
    "time": "12:00 PM",
    "peopleSize": "400",
    "location": "Houston, TX",
    "eventType": "Offline",
    "price": "$799",
    "status": "Published"
  },
  {
    "image": "assets/images/brands/img-25.png",
    "eventName": "Quantum Computing Expo",
    "eventDate": "2024-08-20",
    "time": "09:30 AM",
    "peopleSize": "300",
    "location": "Cambridge, MA",
    "eventType": "Online",
    "price": "$599",
    "status": "Coming Soon"
  },
  {
    "image": "assets/images/brands/img-26.png",
    "eventName": "5G & Connectivity Summit",
    "eventDate": "2024-09-30",
    "time": "10:30 AM",
    "peopleSize": "800",
    "location": "Philadelphia, PA",
    "eventType": "Offline",
    "price": "$699",
    "status": "Published"
  },
  {
    "image": "assets/images/brands/img-27.png",
    "eventName": "Smart Home Conference",
    "eventDate": "2024-10-15",
    "time": "11:00 AM",
    "peopleSize": "500",
    "location": "Columbus, OH",
    "eventType": "Online",
    "price": "$399",
    "status": "Coming Soon"
  },
  {
    "image": "assets/images/brands/img-28.png",
    "eventName": "VR/AR Developers Conference",
    "eventDate": "2024-11-22",
    "time": "12:00 PM",
    "peopleSize": "600",
    "location": "Los Angeles, CA",
    "eventType": "Offline",
    "price": "$899",
    "status": "Published"
  },
  {
    "image": "assets/images/brands/img-05.png",
    "eventName": "Nanotechnology Summit",
    "eventDate": "2024-12-08",
    "time": "09:00 AM",
    "peopleSize": "200",
    "location": "Albany, NY",
    "eventType": "Online",
    "price": "$499",
    "status": "Coming Soon"
  },
  {
    "image": "assets/images/brands/img-06.png",
    "eventName": "E-Sports Conference",
    "eventDate": "2024-07-18",
    "time": "10:00 AM",
    "peopleSize": "900",
    "location": "Las Vegas, NV",
    "eventType": "Offline",
    "price": "$799",
    "status": "Expired"
  },
  {
    "image": "assets/images/brands/img-07.png",
    "eventName": "BioTech World Congress",
    "eventDate": "2024-08-28",
    "time": "11:00 AM",
    "peopleSize": "700",
    "location": "San Francisco, CA",
    "eventType": "Offline",
    "price": "$1099",
    "status": "Published"
  },
  {
    "image": "assets/images/brands/img-08.png",
    "eventName": "AgriTech Summit",
    "eventDate": "2024-09-14",
    "time": "12:00 PM",
    "peopleSize": "500",
    "location": "Des Moines, IA",
    "eventType": "Online",
    "price": "$699",
    "status": "Coming Soon"
  },
  {
    "image": "assets/images/brands/img-09.png",
    "eventName": "EdTech Innovations Forum",
    "eventDate": "2024-10-05",
    "time": "09:30 AM",
    "peopleSize": "400",
    "location": "Austin, TX",
    "eventType": "Offline",
    "price": "$499",
    "status": "Published"
  }
]
